{
  "id": "multi-user-management",
  "category": "Authentication",
  "title": "Multi-User Management and Permissions",
  "description": "Admin interface for managing multiple users with role-based permissions (admin, editor, viewer). Admins can create users, reset passwords, and assign Emby servers. Enables household or team sharing of ACDB instance.",
  "status": "backlog",
  "priority": 3,
  "complexity": "complex",
  "dependencies": [],
  "createdAt": "2026-01-14T22:02:23.976Z",
  "updatedAt": "2026-01-14T22:02:23.976Z"
}